peframe/__init__.py
peframe/peframe.py
peframe/peframecli.py
peframe/config/config-peframe.json
peframe/modules/__init__.py
peframe/modules/apialert.py
peframe/modules/autocomplete.py
peframe/modules/directories.py
peframe/modules/features.py
peframe/modules/fileurl.py
peframe/modules/functions.py
peframe/modules/macro.py
peframe/modules/meta.py
peframe/modules/sections.py
peframe/modules/stringstat.py
peframe/modules/virustotal.py
peframe/modules/yara_check.py
peframe/signatures/stringsmatch.json
peframe/signatures/yara_plugins/doc/JJencode.yar
peframe/signatures/yara_plugins/doc/Javascript_exploit_and_obfuscation.yar
peframe/signatures/yara_plugins/doc/Maldoc_APT10_MenuPass.yar
peframe/signatures/yara_plugins/doc/Maldoc_APT19_CVE-2017-1099.yar
peframe/signatures/yara_plugins/doc/Maldoc_APT_OLE_JSRat.yar
peframe/signatures/yara_plugins/doc/Maldoc_CVE-2017-0199.yar
peframe/signatures/yara_plugins/doc/Maldoc_CVE_2017_11882.yar
peframe/signatures/yara_plugins/doc/Maldoc_CVE_2017_8759.yar
peframe/signatures/yara_plugins/doc/Maldoc_Contains_VBE_File.yar
peframe/signatures/yara_plugins/doc/Maldoc_DDE.yar
peframe/signatures/yara_plugins/doc/Maldoc_Dridex.yar
peframe/signatures/yara_plugins/doc/Maldoc_Hidden_PE_file.yar
peframe/signatures/yara_plugins/doc/Maldoc_MIME_ActiveMime_b64.yar
peframe/signatures/yara_plugins/doc/Maldoc_PowerPointMouse.yar
peframe/signatures/yara_plugins/doc/Maldoc_Suspicious_OLE_target.yar
peframe/signatures/yara_plugins/doc/Maldoc_UserForm.yar
peframe/signatures/yara_plugins/doc/Maldoc_VBA_macro_code.yar
peframe/signatures/yara_plugins/doc/Maldoc_Word_2007_XML_Flat_OPC.yar
peframe/signatures/yara_plugins/doc/Maldoc_malrtf_ole2link.yar
peframe/signatures/yara_plugins/doc/maldoc_somerules.yar
peframe/signatures/yara_plugins/doc/pdf/Maldoc_PDF.yar
peframe/signatures/yara_plugins/pe/antidebug_antivm.yar
peframe/signatures/yara_plugins/pe/crypto_signatures.yar
peframe/signatures/yara_plugins/pe/packer.yar
peframe_ds-7.0.0.dist-info/licenses/LICENSE
peframe_ds-7.0.0.dist-info/METADATA
peframe_ds-7.0.0.dist-info/WHEEL
peframe_ds-7.0.0.dist-info/entry_points.txt
peframe_ds-7.0.0.dist-info/top_level.txt
peframe_ds-7.0.0.dist-info/RECORD
