Metadata-Version: 2.4
Name: peframe-ds
Version: 7.0.0
Summary: peframe is an open source tool to perform static analysis on Portable Executable malware and malicious MS Office documents.
Author-email: "Gianni guelfoweb Amato and Corey Forman (digitalsleuth)" <github@digitalsleuth.ca>
Maintainer-email: "Corey Forman (digitalsleuth)" <github@digitalsleuth.ca>
Project-URL: Homepage, https://github.com/digitalsleuth/peframe
Keywords: digital forensics,dfir,peframe,portable executable,malware,office
Classifier: Development Status :: 5 - Production/Stable
Classifier: Programming Language :: Python :: 3
Classifier: Programming Language :: Python :: 3.6
Classifier: Programming Language :: Python :: 3.7
Classifier: Programming Language :: Python :: 3.8
Classifier: Programming Language :: Python :: 3.9
Classifier: Programming Language :: Python :: 3.10
Classifier: Programming Language :: Python :: 3.11
Classifier: Programming Language :: Python :: 3.12
Classifier: Operating System :: OS Independent
Requires-Python: >=3.8
License-File: LICENSE
Requires-Dist: pefile
Requires-Dist: requests
Requires-Dist: readline; platform_system != "Windows"
Requires-Dist: pyreadline3; platform_system == "Windows"
Requires-Dist: python-magic-bin; platform_system == "Windows"
Requires-Dist: python-magic; platform_system != "Windows"
Requires-Dist: yara-python
Requires-Dist: oletools
Requires-Dist: cryptography
Dynamic: license-file
